<?xml version="1.0" encoding="UTF-8"?>
<!DOCTYPE nitf SYSTEM "http://www.nitf.org/IPTC/NITF/3.3/specification/dtd/nitf-3-3.dtd">
<nitf change.date="June 10, 2005" change.time="19:30" version="-//IPTC//DTD NITF 3.3//EN">
  <head>
    <title>NEWS SUMMARY</title>
    <meta content="27FORS$03" name="slug"/>
    <meta content="27" name="publication_day_of_month"/>
    <meta content="8" name="publication_month"/>
    <meta content="2004" name="publication_year"/>
    <meta content="Friday" name="publication_day_of_week"/>
    <meta content="Metropolitan Desk" name="dsk"/>
    <meta content="2" name="print_page_number"/>
    <meta content="A" name="print_section"/>
    <meta content="3" name="print_column"/>
    <meta content="New York and Region" name="online_sections"/>
    <docdata>
      <doc-id id-string="1606917"/>
      <doc.copyright holder="The New York Times" year="2004"/>
      <identified-content>
        <classifier class="indexing_service" type="descriptor">NO INDEX TERMS FROM NYTIMES</classifier>
        <classifier class="online_producer" type="types_of_material">Summary</classifier>
        <classifier class="online_producer" type="taxonomic_classifier">Top/News/New York and Region</classifier>
      </identified-content>
    </docdata>
    <pubdata date.publication="20040827T000000" ex-ref="http://query.nytimes.com/gst/fullpage.html?res=9A02E4DE113EF934A1575BC0A9629C8B63" item-length="999" name="The New York Times" unit-of-measure="word"/>
  </head>
  <body>
    <body.head>
      <hedline>
        <hl1>NEWS SUMMARY</hl1>
      </hedline>
    </body.head>
    <body.content>
      <block class="lead_paragraph">
        <p>INTERNATIONAL</p>
        <p>A3-11</p>
        <p>Tentative Najaf Agreement After a Day of Bloodshed  Aides to Iraq's most powerful Shiite leader, Grand Ayatollah Ali al-Sistani, said they had reached a tentative agreement to end the siege in Najaf, following a day of chaos and bloodshed that left at least 74 Iraqis dead and more than 300 wounded.</p>
        <p>A1</p>
        <p>Classified parts of the report by three Army generals on the abuses at Abu Ghraib prison say Lt. Gen. Ricardo S. Sanchez, the former top commander in Iraq, approved the use of some severe interrogation practices intended to be limited to captives held in Guantánamo Bay, Cuba, and Afghanistan.</p>
        <p>A1</p>
      </block>
      <block class="full_text">
        <p>INTERNATIONAL</p>
        <p>A3-11</p>
        <p>Tentative Najaf Agreement After a Day of Bloodshed  Aides to Iraq's most powerful Shiite leader, Grand Ayatollah Ali al-Sistani, said they had reached a tentative agreement to end the siege in Najaf, following a day of chaos and bloodshed that left at least 74 Iraqis dead and more than 300 wounded.</p>
        <p>A1</p>
        <p>Classified parts of the report by three Army generals on the abuses at Abu Ghraib prison say Lt. Gen. Ricardo S. Sanchez, the former top commander in Iraq, approved the use of some severe interrogation practices intended to be limited to captives held in Guantánamo Bay, Cuba, and Afghanistan.</p>
        <p>A1</p>
        <p>Medical ethicists and the Army itself said that the failures of Army medical staff to prevent and report torture at Abu Ghraib prison shows the need for more investigation and better training.</p>
        <p>A10</p>
        <p>Former Chilean Dictator's Case  Chile's Supreme Court stripped the former dictator Augusto Pinochet of immunity from prosecution, raising hopes of victims that he may finally face trial for abuses during his 17-year rule. The ruling is the latest decision in cases that accuse him of ordering to kidnap, torture and kill leftists.</p>
        <p>A3</p>
        <p>Clean Water Problems in Africa  Sub-Saharan Africa is lagging far behind the rest of the developing world in access to clean water, with more than 4 out of 10 people still relying on rivers, ponds or other unsafe sources of drinking water, according to a United Nations report. The report blamed conflict, political instability, population growth and the low priority that is given to water and sanitation.</p>
        <p>A4</p>
        <p>Little Progress in Russia Query  The flight recorders of the two crashed Russian airliners were damaged and could provide little help in determining the cause of the twin disasters, which killed at least 89 people. On what was an official day of mourning in Russia, officials continued to offer incomplete and, at times, contradictory statements about what happened.</p>
        <p>A8</p>
        <p>NATIONAL</p>
        <p>A12-18</p>
        <p>Bush Declines to Condemn Ads on Kerry's War Record  President Bush said he did not believe Senator John Kerry lied about his war record, but he declined to condemn the commercial paid for by a veterans group contending that Mr. Kerry came by his medals dishonestly.</p>
        <p>A1</p>
        <p>Census Shows Growth of Poor  The number of people in poverty grew in 2003 for the third straight year, the government reported, in a sign of a long slump in the job markets.</p>
        <p>A1</p>
        <p>The number of people without health insurance rose 1.4 million, to a record 45 million last year.</p>
        <p>C1</p>
        <p>Seizing on the census report, Senator John Kerry challenged the president to weekly debates until Election Day.</p>
        <p>A18</p>
        <p>Strengthening Intelligence Role  President Bush is preparing to issue an executive order that would designate the director of central intelligence to fill much of the role envisioned for a future national intelligence director, officials who have been briefed on the plan said.</p>
        <p>A1</p>
        <p>Suspect Says He's in Al Qaeda  A 36-year-old Yemeni on trial at Guantánamo Bay for conspiracy to commit terrorism said he was a member of Al Qaeda and if he were not allowed to represent himself he would boycott the trial.</p>
        <p>A14</p>
        <p>Ruling Against Abortion Ban  A federal judge ruled that a law banning a rarely used method of abortion was unconstitutional because it did not exempt cases where the procedure might be necessary to protect a woman's health.</p>
        <p>A12</p>
        <p>Problem With Flu Vaccine  A manufacturer of influenza vaccine detected a contamination problem in its new vaccine supply and delayed the release of 50 million doses.</p>
        <p>A14</p>
        <p>NEW YORK/REGION</p>
        <p>B1-8</p>
        <p>New Yorkers Are Uneasy As Convention Week Nears  Half of all New Yorkers are awaiting the Republican National Convention with a mix of dread and unease, according to a New York Times/CBS News poll.</p>
        <p>A1</p>
        <p>Protesters offered a preview of what delegates may expect when they arrive this weekend: spontaneous acts at high-profile locations meant to draw maximum attention. At least 21 people were arrested at three events in Manhattan.</p>
        <p>B1</p>
        <p>The convention has triggered an intense reaction among New York artists, as political fervor is being translated into painting, sculpture, Web art and political ephemera.</p>
        <p>E23</p>
        <p>69 People Linked to Drug Ring  Sixty-nine people, most of them members of five closely linked families, were accused of cooperating as one narcotics trafficker by peddling heroin and cocaine in Brooklyn housing projects, prosecutors said.</p>
        <p>B1</p>
        <p>WEEKEND</p>
        <p>E1-22;E23-30</p>
        <p>ESCAPES</p>
        <p>F1-12</p>
        <p>OBITUARIES</p>
        <p>A19</p>
        <p>SPORTSFRIDAY</p>
        <p>D1-12</p>
        <p>U.S. Women Win Soccer Gold  The United States beat Brazil in overtime, 2-1, to win the gold medal in women's soccer.</p>
        <p>D1</p>
        <p>China Gains as Olympic Power  China is running a close second to the United States in the medal count. The country's success remains largely confined to individual sports.</p>
        <p>D10</p>
        <p>BUSINESS DAY</p>
        <p>C1-9</p>
        <p>Old Subsidies Collected  Student loan corporations are taking advantage of a loophole in the law, billing the federal government nearly $1 billion a year for a subsidy that was supposed to have faded away, government data show.</p>
        <p>C1</p>
        <p>Criminal Activity on the Web  The Justice Department announced that more than 150 people had been arrested, charged or convicted in the last three months in a wide-ranging sweep of criminal activity on the Internet.</p>
        <p>C1</p>
        <p>Van Safety Underscored  Federal crash statistics show that there were 11.2 deaths for every 100,000 registered vans last year, with 16.42 deaths in sport utility vehicles, 14.85 in passenger cars and 15.17 in pickup trucks.</p>
        <p>C1</p>
        <p>Business Digest</p>
        <p>C1</p>
        <p>World Business</p>
        <p>W1</p>
        <p>EDITORIAL</p>
        <p>A20-21</p>
        <p>Editorials: Abu Ghraib, the next step; warming to global warming; Sunday in the park; warm and fuzzy Olympians.</p>
        <p>Columns: Bob Herbert, Paul Krugman.</p>
        <p>Crossword</p>
        <p>E30  TV Listings</p>
        <p>E22  Public Lives</p>
        <p>B2  Weather</p>
        <p>C10</p>
      </block>
    </body.content>
  </body>
</nitf>
